taas/__init__.py
taas/config.py
taas/multiprocess_reader.py
taas/optimized_multiprocess_reader.py
taas/reader.py
taas/simple_reader.py
taas/taas_data_loader.py
taas/taas_data_server.py
taas/writer.py
taas/protos/__init__.py
taas/protos/data_consumer_pb2.py
taas/protos/data_consumer_pb2_grpc.py
taas/protos/data_provider_pb2.py
taas/protos/data_provider_pb2_grpc.py
taas-0.9.2.dist-info/METADATA
taas-0.9.2.dist-info/WHEEL
taas-0.9.2.dist-info/top_level.txt
taas-0.9.2.dist-info/RECORD
