Metadata-Version: 2.1
Name: taas
Version: 0.9.2
Summary: Yandex DataSphere TaaS library
Home-page: UNKNOWN
Author: Yandex
License: MIT
Platform: UNKNOWN
Requires-Dist: grpcio
Requires-Dist: protobuf
